{
  "project_info": {
    "project_number": "374322812269",
    "project_id": "shop-a9abf",
    "storage_bucket": "shop-a9abf.firebasestorage.app"
  },
  "client": [
    {
      "client_info": {
        "mobilesdk_app_id": "1:374322812269:android:dcd5e5270ab158bb3ff664",
        "android_client_info": {
          "package_name": "com.example.mainproject"
        }
      },
      "oauth_client": [],
      "api_key": [
        {
          "current_key": "AIzaSyAJIqOI-x5a93dglLgL6AS2p-q-LgfG1kA"
        }
      ],
      "services": {
        "appinvite_service": {
          "other_platform_oauth_client": []
        }
      }
    }
  ],
  "configuration_version": "1"
}